gstreamer_plugins_runtime-1.27.90.data/purelib/gstreamer_plugins_runtime/__init__.py
gstreamer_plugins_runtime-1.27.90.data/purelib/gstreamer_plugins_runtime/bin/FLAC-8.dll
gstreamer_plugins_runtime-1.27.90.data/purelib/gstreamer_plugins_runtime/bin/SvtAv1Enc.dll
gstreamer_plugins_runtime-1.27.90.data/purelib/gstreamer_plugins_runtime/bin/SvtJpegxs.dll
gstreamer_plugins_runtime-1.27.90.data/purelib/gstreamer_plugins_runtime/bin/ass-9.dll
gstreamer_plugins_runtime-1.27.90.data/purelib/gstreamer_plugins_runtime/bin/avcodec-61.dll
gstreamer_plugins_runtime-1.27.90.data/purelib/gstreamer_plugins_runtime/bin/avfilter-10.dll
gstreamer_plugins_runtime-1.27.90.data/purelib/gstreamer_plugins_runtime/bin/avformat-61.dll
gstreamer_plugins_runtime-1.27.90.data/purelib/gstreamer_plugins_runtime/bin/avutil-59.dll
gstreamer_plugins_runtime-1.27.90.data/purelib/gstreamer_plugins_runtime/bin/dav1d.dll
gstreamer_plugins_runtime-1.27.90.data/purelib/gstreamer_plugins_runtime/bin/dv-4.dll
gstreamer_plugins_runtime-1.27.90.data/purelib/gstreamer_plugins_runtime/bin/dvdnav-4.dll
gstreamer_plugins_runtime-1.27.90.data/purelib/gstreamer_plugins_runtime/bin/dvdread-8.dll
gstreamer_plugins_runtime-1.27.90.data/purelib/gstreamer_plugins_runtime/bin/fmt.dll
gstreamer_plugins_runtime-1.27.90.data/purelib/gstreamer_plugins_runtime/bin/ges-1.0-0.dll
gstreamer_plugins_runtime-1.27.90.data/purelib/gstreamer_plugins_runtime/bin/gstrtspserver-1.0-0.dll
gstreamer_plugins_runtime-1.27.90.data/purelib/gstreamer_plugins_runtime/bin/json-glib-1.0-0.dll
gstreamer_plugins_runtime-1.27.90.data/purelib/gstreamer_plugins_runtime/bin/lcevc_dec_api.dll
gstreamer_plugins_runtime-1.27.90.data/purelib/gstreamer_plugins_runtime/bin/lcevc_dec_legacy.dll
gstreamer_plugins_runtime-1.27.90.data/purelib/gstreamer_plugins_runtime/bin/lcevc_dec_pipeline_cpu.dll
gstreamer_plugins_runtime-1.27.90.data/purelib/gstreamer_plugins_runtime/bin/lcevc_dec_pipeline_legacy.dll
gstreamer_plugins_runtime-1.27.90.dist-info/METADATA
gstreamer_plugins_runtime-1.27.90.dist-info/WHEEL
gstreamer_plugins_runtime-1.27.90.dist-info/top_level.txt
gstreamer_plugins_runtime-1.27.90.dist-info/RECORD
