Metadata-Version: 2.4
Name: gstreamer_plugins_runtime
Version: 1.27.90
Summary: GStreamer 1.0
Home-page: http://gstreamer.freedesktop.org
Author: GStreamer Project
License: MPL-2.0 AND BSD-2-Clause-Patent AND GPL-2.0-or-later AND LGPL-2.1-or-later AND BSD-3-Clause AND Misc AND curl AND Apache-2.0 AND MIT AND LGPL-3.0-only AND BSD-2-Clause AND blessing AND BSD-3-Clause-Clear AND LGPL-2.0-or-later AND libtiff AND ISC AND MPL-1.1
Classifier: Development Status :: 4 - Beta
Classifier: Intended Audience :: Developers
Classifier: Programming Language :: Python :: 3
Classifier: Topic :: Multimedia :: Graphics
Classifier: Topic :: Multimedia :: Sound/Audio
Classifier: Topic :: Multimedia :: Video
Classifier: Topic :: Software Development
Classifier: Topic :: Utilities
Classifier: Environment :: MacOS X
Classifier: Operating System :: MacOS :: MacOS X
Classifier: Environment :: Win32 (MS Windows)
Classifier: Operating System :: Microsoft :: Windows
Requires-Python: >= 3.14
Requires-Dist: gstreamer_runtime~=1.27.90
Dynamic: author
Dynamic: classifier
Dynamic: home-page
Dynamic: license
Dynamic: requires-dist
Dynamic: requires-python
Dynamic: summary
